{
  "asof": "2026-04-16",
  "generatedAt": "2026-04-16T13:25:13.097Z",
  "data": {
    "ref": {
      "value": 130.6756,
      "change": 0.09,
      "percent": 0.07
    },
    "tma": {
      "value": 131.2275,
      "change": -0.12,
      "percent": -0.09
    },
    "euro_achat": {
      "value": 153.5603,
      "change": 0.42,
      "percent": 0.27
    },
    "euro_vente": {
      "value": 154.4494,
      "change": 0.6,
      "percent": 0.39
    },
    "peso_dom_achat": {
      "value": 2.1854,
      "change": 0.01,
      "percent": 0.3
    },
    "peso_dom_vente": {
      "value": 2.1981,
      "change": 0.01,
      "percent": 0.42
    },
    "dol_can_achat": {
      "value": 94.685,
      "change": 0.3,
      "percent": 0.32
    },
    "dol_can_vente": {
      "value": 95.2333,
      "change": 0.41,
      "percent": 0.44
    },
    "marche_banc_achat": {
      "value": 130.4593,
      "change": 0.14,
      "percent": 0.11
    },
    "marche_banc_vente": {
      "value": 131.2275,
      "change": -0.12,
      "percent": -0.09
    }
  }
}
