{
  "asof": "2026-04-29",
  "generatedAt": "2026-04-29T13:26:09.438Z",
  "data": {
    "ref": {
      "value": 130.5543,
      "change": -0.07,
      "percent": -0.06
    },
    "tma": {
      "value": 131.0676,
      "change": -0.22,
      "percent": -0.17
    },
    "euro_achat": {
      "value": 152.6109,
      "change": -0.21,
      "percent": -0.13
    },
    "euro_vente": {
      "value": 153.3866,
      "change": -0.17,
      "percent": -0.11
    },
    "peso_dom_achat": {
      "value": 2.1933,
      "change": 0,
      "percent": 0.21
    },
    "peso_dom_vente": {
      "value": 2.2045,
      "change": 0.01,
      "percent": 0.25
    },
    "dol_can_achat": {
      "value": 95.3409,
      "change": -0.15,
      "percent": -0.16
    },
    "dol_can_vente": {
      "value": 95.8254,
      "change": -0.13,
      "percent": -0.13
    },
    "marche_banc_achat": {
      "value": 130.2571,
      "change": -0.12,
      "percent": -0.09
    },
    "marche_banc_vente": {
      "value": 131.0676,
      "change": -0.22,
      "percent": -0.17
    }
  }
}
