{
  "generatedAt": "2026-04-18T06:40:35.158Z",
  "asof": "2026-04-16",
  "transactions": {
    "volume_achat": 14416058.65,
    "volume_vente": 13865149.11,
    "pct_volume_achat": -39.01396716147065,
    "pct_volume_vente": -41.592933811271195
  },
  "marche_bancaire": {
    "achat": 130.3448,
    "vente": 131.1903,
    "pct_achat": -0.08776683609372495,
    "pct_vente": -0.028347716751431187
  },
  "interventions": {
    "intervention_us_achat": 0,
    "intervention_us_vente": 0,
    "intervention_euro_achat": 0,
    "intervention_euro_vente": 0,
    "total_usd": 0,
    "total_eur": 0,
    "total_usd_plus_eur": 0,
    "pct_total_usd_plus_eur": null
  },
  "autres_devises": {
    "euro_vente": 154.6369,
    "pct_euro_vente": 0.12139898244991564,
    "euro_achat": 154.0182,
    "peso_dom_achat": 2.1769,
    "peso_dom_vente": 2.1856,
    "dol_can_achat": 94.9967,
    "dol_can_vente": 95.3783
  },
  "best_bank": {
    "best_buy_usd": {
      "bank": "Unibank",
      "field": "unibank_achat",
      "value": 129.75
    },
    "best_sell_usd": {
      "bank": "Unibank",
      "field": "unibank_vente",
      "value": 131.75
    }
  }
}