{
  "generatedAt": "2026-07-06T10:58:39.932Z",
  "asof": "2026-07-03",
  "transactions": {
    "volume_achat": 13863325.1,
    "volume_vente": 13615793.84,
    "pct_volume_achat": 4.662176054191485,
    "pct_volume_vente": 2.110593428628451
  },
  "marche_bancaire": {
    "achat": 130.1956,
    "vente": 131.2389,
    "pct_achat": -0.02649157145696732,
    "pct_vente": 0.08312368117417071
  },
  "interventions": {
    "intervention_us_achat": 0,
    "intervention_us_vente": 0,
    "intervention_euro_achat": 0,
    "intervention_euro_vente": 0,
    "total_usd": 0,
    "total_eur": 0,
    "total_usd_plus_eur": 0,
    "pct_total_usd_plus_eur": null
  },
  "autres_devises": {
    "euro_vente": 149.9077,
    "pct_euro_vente": 0.5906967443570816,
    "euro_achat": 149.2312,
    "peso_dom_achat": 2.2126,
    "peso_dom_vente": 2.2227,
    "dol_can_achat": 92.0449,
    "dol_can_vente": 92.4622
  },
  "best_bank": {
    "best_buy_usd": {
      "bank": "BUH",
      "field": "buh_achat",
      "value": 129.25
    },
    "best_sell_usd": {
      "bank": "Unibank",
      "field": "unibank_vente",
      "value": 131.5
    }
  }
}